mieun_mul/__init__.py
mieun_mul/mieun_mul.py
mieun_mul-0.1.0.dist-info/METADATA
mieun_mul-0.1.0.dist-info/WHEEL
mieun_mul-0.1.0.dist-info/top_level.txt
mieun_mul-0.1.0.dist-info/RECORD
