Metadata-Version: 2.1
Name: mieun_mul
Version: 0.1.0
Summary: Default template for PDM package
Author-email: hahahellooo <hahahello777@gmail.com>
License: MIT
Requires-Python: >=3.9
